{
	"grammars": [
		{
			"name": "datazinc",
			"camelcase": "Datazinc",
			"scope": "source.datazinc",
			"path": ".",
			"file-types": ["dzn"]
		}
	],
	"metadata": {
		"version": "0.1.0",
		"license": "MPL-2.0",
		"description": "DataZinc grammer for tree-sitter",
		"authors": [
			{
				"name": "Jip J. Dekker",
				"email": "jip.dekker@monash.edu",
				"url": "https://dekker.one/"
			}
		],
		"links": {
			"repository": "git+https://github.com/shackle-rs/shackle.git"
		}
	},
	"bindings": {
		"c": true,
		"go": true,
		"node": true,
		"python": true,
		"rust": true,
		"swift": true
	}
}
